{
  "Family Sans": {
    "$type": "text",
    "$value": "Inter"
  },
  "Family Serif": {
    "$type": "text",
    "$value": "Noto Serif"
  },
  "Family Mono": {
    "$type": "text",
    "$value": "Roboto Mono"
  },
  "Weight Light Italic": {
    "$type": "text",
    "$value": "Light Italic"
  },
  "Weight Regular Italic": {
    "$type": "text",
    "$value": "Italic"
  },
  "Weight Bold Italic": {
    "$type": "text",
    "$value": "Bold Italic"
  },
  "Weight Thin Italic": {
    "$type": "text",
    "$value": "Thin Italic"
  },
  "Weight Extralight Italic": {
    "$type": "text",
    "$value": "Extra Light Italic"
  },
  "Weight Medium Italic": {
    "$type": "text",
    "$value": "Medium Italic"
  },
  "Weight Semibold Italic": {
    "$type": "text",
    "$value": "Semi Bold Italic"
  },
  "Weight Extra Bold Italic": {
    "$type": "text",
    "$value": "Extra Bold Italic"
  },
  "Weight Black Italic": {
    "$type": "text",
    "$value": "Black Italic"
  },
  "Weight Thin": {
    "$type": "dimension",
    "$value": "6.25rem"
  },
  "Weight Extra Light": {
    "$type": "dimension",
    "$value": "12.5rem"
  },
  "Weight Light": {
    "$type": "dimension",
    "$value": "18.75rem"
  },
  "Weight Regular": {
    "$type": "dimension",
    "$value": "25rem"
  },
  "Weight Medium": {
    "$type": "dimension",
    "$value": "31.25rem"
  },
  "Weight Semibold": {
    "$type": "dimension",
    "$value": "37.5rem"
  },
  "Weight Bold": {
    "$type": "dimension",
    "$value": "43.75rem"
  },
  "Weight Extra Bold": {
    "$type": "dimension",
    "$value": "50rem"
  },
  "Weight Black": {
    "$type": "dimension",
    "$value": "56.25rem"
  },
  "Scale 10": {
    "$type": "dimension",
    "$value": "4.5rem"
  },
  "Scale 09": {
    "$type": "dimension",
    "$value": "4rem"
  },
  "Scale 08": {
    "$type": "dimension",
    "$value": "3rem"
  },
  "Scale 07": {
    "$type": "dimension",
    "$value": "2.5rem"
  },
  "Scale 06": {
    "$type": "dimension",
    "$value": "2rem"
  },
  "Scale 05": {
    "$type": "dimension",
    "$value": "1.5rem"
  },
  "Scale 04": {
    "$type": "dimension",
    "$value": "1.25rem"
  },
  "Scale 03": {
    "$type": "dimension",
    "$value": "1rem"
  },
  "Scale 02": {
    "$type": "dimension",
    "$value": "0.875rem"
  },
  "Scale 01": {
    "$type": "dimension",
    "$value": "0.75rem"
  }
}